tests/__init__.py
tests/test_certishop.py
wallid_certishop-0.1.1.dist-info/LICENSE
wallid_certishop-0.1.1.dist-info/METADATA
wallid_certishop-0.1.1.dist-info/WHEEL
wallid_certishop-0.1.1.dist-info/top_level.txt
wallid_certishop-0.1.1.dist-info/RECORD
