Metadata-Version: 2.1
Name: wallid-certishop
Version: 0.1.1
Summary: A Python library for managing verifiable credentials with WalliD CertiShop.
Home-page: https://github.com/walliDprotocol/CertiShop_lib
Author: Filipe Veiga
Author-email: info@wallid.io
Classifier: Programming Language :: Python :: 3
Classifier: License :: OSI Approved :: MIT License
Classifier: Operating System :: OS Independent
Requires-Python: >=3.6
License-File: LICENSE
Requires-Dist: requests
